{
  "run_id": "20260507T051200Z_a1_cross_3733900",
  "experiment": "experiments.02_closed_set_reid",
  "args": ["--all"],
  "git_sha": "3733900c7f6e761561364c29fd102fcafc6af229",
  "hardware": "Colab NVIDIA L4 (23 GB)",
  "torch_version": "2.10.0+cu128",
  "completed_at_utc": "2026-05-07T05:12:00Z",
  "notes": "First A1 re-run with EEGNet input_scale=1e6 (volts -> microvolts) fix in models/eegnet.py. EEGNet now learns the cross-subject task at task_acc=0.388 (>chance 0.25) and leaks subject identity at logreg top-1 0.411 (chance 0.0096; 43x lift). FBCSP and Riemann re-ID numbers reproduce the prior run within bootstrap CI, validating that the EEGNet rerun did not perturb their entries.",
  "wall_seconds": {
    "prefetch_imagery": 35.4,
    "data_load_and_window": 90.3,
    "eegnet_train_and_score": 274.6,
    "eegnet_attack": 23.0,
    "fbcsp_train_and_score": 629.6,
    "fbcsp_attack": 250.5,
    "riemann_train_and_score": 259.5,
    "riemann_attack": 91.0
  },
  "victim_metrics": {
    "eegnet": {"task_acc_test": 0.388},
    "fbcsp_lda": {"task_acc_test": 0.268},
    "riemann_ts_lr": {"task_acc_test": 0.350}
  },
  "outputs": [
    "results/02_closed_set_reid.json",
    "figures/02_closed_set_reid.pdf"
  ]
}
